viburnum/__init__.py
viburnum/application/__init__.py
viburnum/application/base.py
viburnum/application/connectors.py
viburnum/application/handlers.py
viburnum/application/resources.py
viburnum/application/types.py
viburnum/cli/__init__.py
viburnum/cli/api_template.py
viburnum/cli/app_template.py
viburnum/cli/job_template.py
viburnum/cli/s3_worker_template.py
viburnum/cli/sqs_worker_template.py
viburnum/deployer/__init__.py
viburnum/deployer/builders.py
viburnum-0.1.6.dist-info/entry_points.txt
viburnum-0.1.6.dist-info/WHEEL
viburnum-0.1.6.dist-info/METADATA
viburnum-0.1.6.dist-info/RECORD
