Metadata-Version: 2.1
Name: viburnum
Version: 0.1.6
Summary: It's abstraction on top of AWS CDK, that helps in building serverless web applications.
Home-page: https://github.com/yarik2215/Viburnum
License: MIT
Keywords: aws,serverless
Author: Yaroslav Martynenko
Author-email: stikblacklabel@gmail.com
Requires-Python: >=3.8,<4.0
Classifier: License :: OSI Approved :: MIT License
Classifier: Programming Language :: Python :: 3
Classifier: Programming Language :: Python :: 3.8
Classifier: Programming Language :: Python :: 3.9
Classifier: Programming Language :: Python :: 3.10
Provides-Extra: deployer
Requires-Dist: aws-cdk-lib (==2.50.0); extra == "deployer"
Requires-Dist: boto3 (>=1.26.8,<2.0.0); extra == "deployer"
Requires-Dist: constructs (>=10.0.0,<11.0.0); extra == "deployer"
Requires-Dist: typer[all] (>=0.7.0,<0.8.0); extra == "deployer"
Project-URL: Repository, https://github.com/yarik2215/Viburnum
